Workbook

Sheet RESUMO
B2: PRESSUPOSTO REAL | F2: Preencha só a aba SAÍDAS. Esta aqui é toda fórmula.
B3: BARRETOS 2026 — 6 câmeras + lentes servo + lentes EF + equipe técnica + montagem | F3: Amarelo = campo para digitar.
B4: Cliente: CLUBE DO COWBOY
B5: Contato: ALEX (034) 99645-0612
B6: Período: 19/08/2026 a 31/08/2026 — 10 diárias
B8: 1. ENTRADAS — o que o cliente paga
B9: DESCRIÇÃO | C9: VALOR | D9: DATA PREVISTA | E9: STATUS | F9: OBS
B10: 1ª parcela (50%) — até 10 dias antes das captações | C10: 40500 | D10: 46241 | E10: A RECEBER | F10: conforme pagamento da Sony · PIX ou transferência
B11: 2ª parcela (50%) — até 10 dias após as captações | C11: 40500 | D11: 46275 | E11: A RECEBER | F11: proposta final Alex: R$ 81.000 (valor 2025 + 8% inflação)
B15: TOTAL ENTRADAS (BRUTO) | C15: =SUM(C10:C14)
B16: IMPOSTO (%) ← edite aqui se mudar | C16: 0.16
B17: (−) IMPOSTO | C17: =ROUND(C15*C16,2)
B18: (=) ENTRADA LÍQUIDA — é com isso que se paga tudo | C18: =C15-C17
B20: 2. SAÍDAS POR ÁREA — vem sozinho da aba SAÍDAS
B21: ÁREA | C21: VALOR | D21: % DA LÍQUIDA | E21: PAGO | F21: A PAGAR
B22: =IF(AREAS!$A$2="","",AREAS!$A$2) | C22: =IF(B22="","",SUMIF(SAIDAS!$B$6:$B$500,B22,SAIDAS!$G$6:$G$500)) | D22: =IF(OR(B22="",$C$18=0),"",C22/$C$18) | E22: =IF(B22="","",SUMIFS(SAIDAS!$G$6:$G$500,SAIDAS!$B$6:$B$500,B22,SAIDAS!$H$6:$H$500,"PAGO")) | F22: =IF(B22="","",C22-E22)
B23: =IF(AREAS!$A$3="","",AREAS!$A$3) | C23: =IF(B23="","",SUMIF(SAIDAS!$B$6:$B$500,B23,SAIDAS!$G$6:$G$500)) | D23: =IF(OR(B23="",$C$18=0),"",C23/$C$18) | E23: =IF(B23="","",SUMIFS(SAIDAS!$G$6:$G$500,SAIDAS!$B$6:$B$500,B23,SAIDAS!$H$6:$H$500,"PAGO")) | F23: =IF(B23="","",C23-E23)
B24: =IF(AREAS!$A$4="","",AREAS!$A$4) | C24: =IF(B24="","",SUMIF(SAIDAS!$B$6:$B$500,B24,SAIDAS!$G$6:$G$500)) | D24: =IF(OR(B24="",$C$18=0),"",C24/$C$18) | E24: =IF(B24="","",SUMIFS(SAIDAS!$G$6:$G$500,SAIDAS!$B$6:$B$500,B24,SAIDAS!$H$6:$H$500,"PAGO")) | F24: =IF(B24="","",C24-E24)
B25: =IF(AREAS!$A$5="","",AREAS!$A$5) | C25: =IF(B25="","",SUMIF(SAIDAS!$B$6:$B$500,B25,SAIDAS!$G$6:$G$500)) | D25: =IF(OR(B25="",$C$18=0),"",C25/$C$18) | E25: =IF(B25="","",SUMIFS(SAIDAS!$G$6:$G$500,SAIDAS!$B$6:$B$500,B25,SAIDAS!$H$6:$H$500,"PAGO")) | F25: =IF(B25="","",C25-E25)
B26: =IF(AREAS!$A$6="","",AREAS!$A$6) | C26: =IF(B26="","",SUMIF(SAIDAS!$B$6:$B$500,B26,SAIDAS!$G$6:$G$500)) | D26: =IF(OR(B26="",$C$18=0),"",C26/$C$18) | E26: =IF(B26="","",SUMIFS(SAIDAS!$G$6:$G$500,SAIDAS!$B$6:$B$500,B26,SAIDAS!$H$6:$H$500,"PAGO")) | F26: =IF(B26="","",C26-E26)
B27: =IF(AREAS!$A$7="","",AREAS!$A$7) | C27: =IF(B27="","",SUMIF(SAIDAS!$B$6:$B$500,B27,SAIDAS!$G$6:$G$500)) | D27: =IF(OR(B27="",$C$18=0),"",C27/$C$18) | E27: =IF(B27="","",SUMIFS(SAIDAS!$G$6:$G$500,SAIDAS!$B$6:$B$500,B27,SAIDAS!$H$6:$H$500,"PAGO")) | F27: =IF(B27="","",C27-E27)
B28: =IF(AREAS!$A$8="","",AREAS!$A$8) | C28: =IF(B28="","",SUMIF(SAIDAS!$B$6:$B$500,B28,SAIDAS!$G$6:$G$500)) | D28: =IF(OR(B28="",$C$18=0),"",C28/$C$18) | E28: =IF(B28="","",SUMIFS(SAIDAS!$G$6:$G$500,SAIDAS!$B$6:$B$500,B28,SAIDAS!$H$6:$H$500,"PAGO")) | F28: =IF(B28="","",C28-E28)
B29: =IF(AREAS!$A$9="","",AREAS!$A$9) | C29: =IF(B29="","",SUMIF(SAIDAS!$B$6:$B$500,B29,SAIDAS!$G$6:$G$500)) | D29: =IF(OR(B29="",$C$18=0),"",C29/$C$18) | E29: =IF(B29="","",SUMIFS(SAIDAS!$G$6:$G$500,SAIDAS!$B$6:$B$500,B29,SAIDAS!$H$6:$H$500,"PAGO")) | F29: =IF(B29="","",C29-E29)
B30: =IF(AREAS!$A$10="","",AREAS!$A$10) | C30: =IF(B30="","",SUMIF(SAIDAS!$B$6:$B$500,B30,SAIDAS!$G$6:$G$500)) | D30: =IF(OR(B30="",$C$18=0),"",C30/$C$18) | E30: =IF(B30="","",SUMIFS(SAIDAS!$G$6:$G$500,SAIDAS!$B$6:$B$500,B30,SAIDAS!$H$6:$H$500,"PAGO")) | F30: =IF(B30="","",C30-E30)
B31: =IF(AREAS!$A$11="","",AREAS!$A$11) | C31: =IF(B31="","",SUMIF(SAIDAS!$B$6:$B$500,B31,SAIDAS!$G$6:$G$500)) | D31: =IF(OR(B31="",$C$18=0),"",C31/$C$18) | E31: =IF(B31="","",SUMIFS(SAIDAS!$G$6:$G$500,SAIDAS!$B$6:$B$500,B31,SAIDAS!$H$6:$H$500,"PAGO")) | F31: =IF(B31="","",C31-E31)
B32: =IF(AREAS!$A$12="","",AREAS!$A$12) | C32: =IF(B32="","",SUMIF(SAIDAS!$B$6:$B$500,B32,SAIDAS!$G$6:$G$500)) | D32: =IF(OR(B32="",$C$18=0),"",C32/$C$18) | E32: =IF(B32="","",SUMIFS(SAIDAS!$G$6:$G$500,SAIDAS!$B$6:$B$500,B32,SAIDAS!$H$6:$H$500,"PAGO")) | F32: =IF(B32="","",C32-E32)
B33: =IF(AREAS!$A$13="","",AREAS!$A$13) | C33: =IF(B33="","",SUMIF(SAIDAS!$B$6:$B$500,B33,SAIDAS!$G$6:$G$500)) | D33: =IF(OR(B33="",$C$18=0),"",C33/$C$18) | E33: =IF(B33="","",SUMIFS(SAIDAS!$G$6:$G$500,SAIDAS!$B$6:$B$500,B33,SAIDAS!$H$6:$H$500,"PAGO")) | F33: =IF(B33="","",C33-E33)
B34: =IF(AREAS!$A$14="","",AREAS!$A$14) | C34: =IF(B34="","",SUMIF(SAIDAS!$B$6:$B$500,B34,SAIDAS!$G$6:$G$500)) | D34: =IF(OR(B34="",$C$18=0),"",C34/$C$18) | E34: =IF(B34="","",SUMIFS(SAIDAS!$G$6:$G$500,SAIDAS!$B$6:$B$500,B34,SAIDAS!$H$6:$H$500,"PAGO")) | F34: =IF(B34="","",C34-E34)
B35: SEM ÁREA — classificar na aba SAÍDAS | C35: =ROUND(SUM(SAIDAS!$G$6:$G$500)-SUM(C22:C34),2)
B36: TOTAL SAÍDAS | C36: =ROUND(SUM(SAIDAS!$G$6:$G$500),2) | D36: =IF($C$18=0,"",C36/$C$18) | E36: =SUMIF(SAIDAS!$H$6:$H$500,"PAGO",SAIDAS!$G$6:$G$500) | F36: =C36-E36
B38: 3. RESULTADO
B39: ENTRADA LÍQUIDA | C39: =C18
B40: (−) TOTAL SAÍDAS | C40: =C36
B41: (=) LUCRO DA YAD | C41: =C18-C36
B42: MARGEM (sobre a entrada bruta) | C42: =IF(C15=0,"",C41/C15)
B44: 4. CAIXA — o que já andou e o que falta
C45: JÁ ANDOU | D45: FALTA
B46: ENTRADAS (recebido / a receber) | C46: =SUMIF(E10:E14,"RECEBIDO",C10:C14) | D46: =C15-C46
B47: SAÍDAS (pago / a pagar) | C47: =E36 | D47: =F36

Sheet AREAS
A1: ÁREAS DE GASTO
A2: EQUIPE | C2: Área nova? Escreva na primeira linha amarela.
A3: TRANSPORTE E LOGÍSTICA | C3: Ela aparece sozinha na listinha da aba SAÍDAS e vira uma linha no RESUMO.
A4: ALIMENTAÇÃO | C4: Não apague área que já tem gasto lançado — o RESUMO perde a linha.
A5: HOSPEDAGEM
A6: EQUIPAMENTO E MANUTENÇÃO
A7: LOCAÇÃO DE TERCEIROS
A8: PRODUÇÃO E DIVERSOS
A9: COMISSÃO

Sheet SAIDAS
B2: SAÍDAS — um gasto por linha
B3: Como usar: 1) escreva o gasto numa linha vazia 2) escolha a ÁREA na listinha da célula 3) preencha QTD e VALOR UNITÁRIO — o TOTAL e o RESUMO se viram sozinhos.
B5: ÁREA | C5: DESCRIÇÃO / QUEM | D5: FUNÇÃO / DETALHE | E5: QTD | F5: VALOR UNITÁRIO | G5: TOTAL | H5: STATUS | I5: DATA PGTO | J5: OBS
B6: EQUIPE | C6: Viny | D6: Assistente técnico geral | E6: 10 | F6: 350 | G6: =IF(OR(E6="",F6=""),"",ROUND(E6*F6,2)) | H6: A PAGAR | J6: diária de referência do orçamento — confirmar o combinado
B7: EQUIPE | C7: Caio | D7: Assistente técnico geral | E7: 10 | F7: 350 | G7: =IF(OR(E7="",F7=""),"",ROUND(E7*F7,2)) | H7: A PAGAR | J7: diária de referência do orçamento — confirmar o combinado
B8: EQUIPE | C8: Cassio | D8: Técnico do sistema | E8: 10 | F8: 800 | G8: =IF(OR(E8="",F8=""),"",ROUND(E8*F8,2)) | H8: A PAGAR | J8: diária de referência do orçamento — confirmar o combinado
B9: EQUIPE | C9: Paulinho | D9: Cinegrafista | E9: 10 | F9: 500 | G9: =IF(OR(E9="",F9=""),"",ROUND(E9*F9,2)) | H9: A PAGAR | J9: diária de referência do orçamento — confirmar o combinado
B10: EQUIPE | C10: Guilherme | D10: Cinegrafista | E10: 10 | F10: 500 | G10: =IF(OR(E10="",F10=""),"",ROUND(E10*F10,2)) | H10: A PAGAR | J10: diária de referência do orçamento — confirmar o combinado
B11: EQUIPE | C11: Rodrigo | D11: Cinegrafista | E11: 10 | F11: 500 | G11: =IF(OR(E11="",F11=""),"",ROUND(E11*F11,2)) | H11: A PAGAR | J11: diária de referência do orçamento — confirmar o combinado
B12: EQUIPE | C12: Kadu | D12: Cinegrafista | E12: 10 | F12: 500 | G12: =IF(OR(E12="",F12=""),"",ROUND(E12*F12,2)) | H12: A PAGAR | J12: diária de referência do orçamento — confirmar o combinado
B13: EQUIPE | C13: Fhilippe | D13: Cinegrafista | E13: 10 | F13: 500 | G13: =IF(OR(E13="",F13=""),"",ROUND(E13*F13,2)) | H13: A PAGAR | J13: diária de referência do orçamento — confirmar o combinado
B14: EQUIPE | C14: Carlos | D14: Responsável do sistema | E14: 10 | F14: 0 | G14: =IF(OR(E14="",F14=""),"",ROUND(E14*F14,2)) | J14: sem valor — entra na equipe para constar na escala
B15: TRANSPORTE E LOGÍSTICA | C15: Combustível — caminhão de equipamento | D15: SP ↔ Barretos, ida e volta | E15: 1 | G15: =IF(OR(E15="",F15=""),"",ROUND(E15*F15,2)) | H15: A PAGAR
B16: TRANSPORTE E LOGÍSTICA | C16: Combustível — carro de apoio | D16: equipe | E16: 1 | G16: =IF(OR(E16="",F16=""),"",ROUND(E16*F16,2)) | H16: A PAGAR
B17: TRANSPORTE E LOGÍSTICA | C17: Pedágio | D17: ida e volta | E17: 1 | G17: =IF(OR(E17="",F17=""),"",ROUND(E17*F17,2)) | H17: A PAGAR
B18: ALIMENTAÇÃO | C18: Alimentação na estrada — ida | D18: equipe | E18: 1 | G18: =IF(OR(E18="",F18=""),"",ROUND(E18*F18,2)) | H18: A PAGAR
B19: ALIMENTAÇÃO | C19: Alimentação na estrada — volta | D19: equipe | E19: 1 | G19: =IF(OR(E19="",F19=""),"",ROUND(E19*F19,2)) | H19: A PAGAR
B20: ALIMENTAÇÃO | C20: Alimentação da equipe durante o evento | D20: 8 pessoas × diárias | G20: =IF(OR(E20="",F20=""),"",ROUND(E20*F20,2)) | H20: A PAGAR | J20: checar o que o Clube do Cowboy cobre de catering
B21: HOSPEDAGEM | C21: Hospedagem da equipe em Barretos | D21: diárias × quartos | G21: =IF(OR(E21="",F21=""),"",ROUND(E21*F21,2)) | H21: A PAGAR | J21: confirmar se é por conta do cliente
B22: EQUIPAMENTO E MANUTENÇÃO | C22: Conserto do caminhão | D22: caminhão que leva o equipamento | E22: 1 | F22: 1500 | G22: =IF(OR(E22="",F22=""),"",ROUND(E22*F22,2)) | H22: A PAGAR | J22: valor aproximado informado pela produção
G23: =IF(OR(E23="",F23=""),"",ROUND(E23*F23,2))
G24: =IF(OR(E24="",F24=""),"",ROUND(E24*F24,2))
G25: =IF(OR(E25="",F25=""),"",ROUND(E25*F25,2))
G26: =IF(OR(E26="",F26=""),"",ROUND(E26*F26,2))
G27: =IF(OR(E27="",F27=""),"",ROUND(E27*F27,2))
G28: =IF(OR(E28="",F28=""),"",ROUND(E28*F28,2))
G29: =IF(OR(E29="",F29=""),"",ROUND(E29*F29,2))
G30: =IF(OR(E30="",F30=""),"",ROUND(E30*F30,2))
G31: =IF(OR(E31="",F31=""),"",ROUND(E31*F31,2))
G32: =IF(OR(E32="",F32=""),"",ROUND(E32*F32,2))
G33: =IF(OR(E33="",F33=""),"",ROUND(E33*F33,2))
G34: =IF(OR(E34="",F34=""),"",ROUND(E34*F34,2))
... G500: =IF(OR(E500="",F500=""),"",ROUND(E500*F500,2))
